libcrypto-3-x64.dll
pyser.pdb
pysercp313-win_amd64.so
zstd.dll
pyserpy/__init__.py
pyserpy/_version.py
pyserpy/legacy.dll
pyserpy/libcrypto-3-x64.dll
pyserpy/libssl-3-x64.dll
pyserpy/pysercp313-win_amd64.so
pyserpy/zstd.dll
rkyv-1.0.1.dist-info/licenses/LICENSE
rkyv-1.0.1.dist-info/METADATA
rkyv-1.0.1.dist-info/WHEEL
rkyv-1.0.1.dist-info/top_level.txt
rkyv-1.0.1.dist-info/RECORD
