Metadata-Version: 2.4
Name: rkyv
Version: 1.0.1
Summary: A high-performance C++ serialization library with Python bindings
Author: rand0mdevel0per
License-Expression: MIT
Project-URL: Source, https://github.com/rand0mdevel0per/pyser
Classifier: Programming Language :: Python :: 3
Classifier: Programming Language :: Python :: 3.8
Classifier: Programming Language :: Python :: 3.9
Classifier: Programming Language :: Python :: 3.10
Classifier: Programming Language :: Python :: 3.11
Classifier: Programming Language :: Python :: 3.12
Classifier: Programming Language :: Python :: 3.13
Classifier: Programming Language :: C++
Classifier: Operating System :: OS Independent
Classifier: Operating System :: Microsoft :: Windows
Classifier: Operating System :: POSIX :: Linux
Classifier: Operating System :: MacOS
Requires-Python: >=3.8
License-File: LICENSE
Provides-Extra: test
Requires-Dist: pytest; extra == "test"
Requires-Dist: zstandard; extra == "test"
Dynamic: license-file
